RFI/RFI.py
RFI/__init__.py
RFI-0.1.12.dist-info/LICENSE.txt
RFI-0.1.12.dist-info/METADATA
RFI-0.1.12.dist-info/WHEEL
RFI-0.1.12.dist-info/top_level.txt
RFI-0.1.12.dist-info/RECORD
