Metadata-Version: 2.1
Name: RFI
Version: 0.1.12
Summary: Feature selections methods for classification and regression
Home-page: https://github.com/AitorHernandez1/RFI
Download-URL: https://github.com/AitorHernandez1/RFI/archive/refs/tags/3.0.tar.gz
Author: Alejandro Santos and Aitor Hernandez
Author-email: aitor.hernanadez.1a@gmail.com
License: MIT
Keywords: feature,regression,classification
Classifier: Development Status :: 3 - Alpha
Classifier: Intended Audience :: Developers
Classifier: Topic :: Software Development :: Build Tools
Classifier: License :: OSI Approved :: MIT License
Classifier: Programming Language :: Python :: 3
Classifier: Programming Language :: Python :: 3.4
Classifier: Programming Language :: Python :: 3.5
Classifier: Programming Language :: Python :: 3.6
License-File: LICENSE.txt
Requires-Dist: pandas
Requires-Dist: sklearn
Requires-Dist: numpy
